MANIFEST.in
README.md
requirements.txt
setup.py
zetapush_python/__init__.py
zetapush_python.egg-info/PKG-INFO
zetapush_python.egg-info/SOURCES.txt
zetapush_python.egg-info/dependency_links.txt
zetapush_python.egg-info/requires.txt
zetapush_python.egg-info/top_level.txt
zetapush_python/client/__init__.py
zetapush_python/client/service.py
zetapush_python/client/zpclient.py
zetapush_python/utils/__init__.py
zetapush_python/utils/constants.py