Metadata-Version: 1.0
Name: zetapush-python
Version: 0.1.4
Summary: Zetapush Python SDK
Home-page: UNKNOWN
Author: Damien Le Dantec
Author-email: damien.le-dantec@zetapush.com
License: MIT
Platform: UNKNOWN
